{
    "data": [
    "{\"location\": \"Constantinople\", \"latitude\": 41.013888888888886, \"longitude\": 28.955555555555556}",
    "{\"location\": \"Bursa\", \"latitude\": 40.18333333333333, \"longitude\": 29.05}",
    "{\"location\": \"Mudurnu\", \"latitude\": 40.46666666666667, \"longitude\": 31.216666666666665}",
    "{\"location\": \"Tarakl%C4%B1\", \"latitude\": 40.39694444444444, \"longitude\": 30.49277777777778}",
    "{\"location\": \"Konya\", \"latitude\": 37.86666666666667, \"longitude\": 32.483333333333334}",
    "{\"location\": \"Adana\", \"latitude\": 37.0, \"longitude\": 35.321333333333335}",
    "{\"location\": \"Antioch\", \"latitude\": 36.20472222222222, \"longitude\": 36.181666666666665}",
    "{\"location\": \"Izmir\", \"latitude\": 38.416666666666664, \"longitude\": 27.133333333333333}",
    "{\"location\": \"Trabzon\", \"latitude\": 41.005, \"longitude\": 39.722500000000004}",
    "{\"location\": \"Baku\", \"latitude\": 40.39527777777778, \"longitude\": 49.882222222222225}",
    "{\"location\": \"Shamakhi\", \"latitude\": 40.63027777777778, \"longitude\": 48.64138888888889}",
    "{\"location\": \"Barda_Azerbaijan\", \"latitude\": 40.37444444444444, \"longitude\": 47.126666666666665}",
    "{\"location\": \"Tbilisi\", \"latitude\": 41.722500000000004, \"longitude\": 44.7925}",
    "{\"location\": \"Batumi\", \"latitude\": 41.645833333333336, \"longitude\": 41.641666666666666}",
    "{\"location\": \"Poti\", \"latitude\": 42.15, \"longitude\": 41.666666666666664}",
    "{\"location\": \"Yerevan\", \"latitude\": 40.18138888888889, \"longitude\": 44.51444444444444}",
    "{\"location\": \"Tyre_Lebanon\", \"latitude\": 33.270833333333336, \"longitude\": 35.19611111111111}",
    "{\"location\": \"Aleppo\", \"latitude\": 36.21666666666667, \"longitude\": 37.166666666666664}",
    "{\"location\": \"Tartus\", \"latitude\": 34.88333333333333, \"longitude\": 35.88333333333333}",
    "{\"location\": \"Homs\", \"latitude\": 34.73083333333334, \"longitude\": 36.70944444444445}",
    "{\"location\": \"Damascus\", \"latitude\": 33.51305555555555, \"longitude\": 36.29194444444444}",
    "{\"location\": \"Palmyra\", \"latitude\": 34.55138888888889, \"longitude\": 38.268055555555556}",
    "{\"location\": \"Raqqa\", \"latitude\": 35.95, \"longitude\": 39.016666666666666}",
    "{\"location\": \"Dura_Europos\", \"latitude\": 34.746944444444445, \"longitude\": 40.730000000000004}",
    "{\"location\": \"Mosul\", \"latitude\": 36.333333333333336, \"longitude\": 43.13333333333333}",
    "{\"location\": \"Erbil\", \"latitude\": 36.191111111111105, \"longitude\": 44.009166666666665}",
    "{\"location\": \"Samarra\", \"latitude\": 34.19833333333333, \"longitude\": 43.87416666666667}",
    "{\"location\": \"Fallujah\", \"latitude\": 33.353611111111114, \"longitude\": 43.779444444444444}",
    "{\"location\": \"Baghdad\", \"latitude\": 33.333333333333336, \"longitude\": 44.38333333333333}",
    "{\"location\": \"Ctesiphon\", \"latitude\": 33.093611111111116, \"longitude\": 44.580555555555556}",
    "{\"location\": \"Baquba\", \"latitude\": 33.75, \"longitude\": 44.63333333333333}",
    "{\"location\": \"Tabriz\", \"latitude\": 38.06666666666667, \"longitude\": 46.3}",
    "{\"location\": \"Zanjan_Iran\", \"latitude\": 36.666666666666664, \"longitude\": 48.483333333333334}",
    "{\"location\": \"Rasht\", \"latitude\": 37.280833333333334, \"longitude\": 49.58305555555556}",
    "{\"location\": \"Kermanshah\", \"latitude\": 34.314166666666665, \"longitude\": 47.065}",
    "{\"location\": \"Hamadan\", \"latitude\": 34.79833333333333, \"longitude\": 48.515}",
    "{\"location\": \"Rey_Iran\", \"latitude\": 35.583333333333336, \"longitude\": 51.43333333333333}",
    "{\"location\": \"Hecatompylos\", \"latitude\": 35.951055555555556, \"longitude\": 54.11280555555556}",
    "{\"location\": \"Sabzevar\", \"latitude\": 36.212500000000006, \"longitude\": 57.68194444444444}",
    "{\"location\": \"Nishapur\", \"latitude\": 36.21333333333334, \"longitude\": 58.795833333333334}",
    "{\"location\": \"Mashhad\", \"latitude\": 36.3, \"longitude\": 59.6}",
    "{\"location\": \"Tus,_Iran\", \"latitude\": 36.45416666666667, \"longitude\": 59.566944444444445}",
    "{\"location\": \"Bam_Iran\", \"latitude\": 29.10611111111111, \"longitude\": 58.356944444444444}",
    "{\"location\": \"Yazd\", \"latitude\": 31.897222222222222, \"longitude\": 54.367777777777775}",
    "{\"location\": \"Qazvin\", \"latitude\": 36.266666666666666, \"longitude\": 50.0}",
    "{\"location\": \"Qumis_Iran\", \"latitude\": 35.951055555555556, \"longitude\": 54.11280555555556}",
    "{\"location\": \"Nisa_Turkmenistan\", \"latitude\": 37.96666666666667, \"longitude\": 58.19499999999999}",
    "{\"location\": \"Merv\", \"latitude\": 37.66277777777778, \"longitude\": 62.192499999999995}",
    "{\"location\": \"Konye-Urgench\", \"latitude\": 42.333333333333336, \"longitude\": 59.15}",
    "{\"location\": \"T%C3%BCrkmenabat\", \"latitude\": 39.083333333333336, \"longitude\": 63.56666666666667}",
    "{\"location\": \"Bukhara\", \"latitude\": 39.766666666666666, \"longitude\": 64.43333333333334}",
    "{\"location\": \"Shahrisabz\", \"latitude\": 39.05, \"longitude\": 66.83333333333333}",
    "{\"location\": \"Samarkand\", \"latitude\": 39.7, \"longitude\": 66.98333333333333}",
    "{\"location\": \"Tashkent\", \"latitude\": 41.3, \"longitude\": 69.26666666666667}",
    "{\"location\": \"Kokand\", \"latitude\": 40.52861111111111, \"longitude\": 70.94250000000001}",
    "{\"location\": \"Andijon\", \"latitude\": 40.78333333333333, \"longitude\": 72.33333333333333}",
    "{\"location\": \"Khujand\", \"latitude\": 40.28333333333333, \"longitude\": 69.63333333333334}",
    "{\"location\": \"Istaravshan\", \"latitude\": 39.91083333333333, \"longitude\": 69.00638888888889}",
    "{\"location\": \"Otrar\", \"latitude\": 42.8525, \"longitude\": 68.30277777777778}",
    "{\"location\": \"Sayram_(city)\", \"latitude\": 42.3, \"longitude\": 69.76666666666667}",
    "{\"location\": \"Taraz\", \"latitude\": 42.9, \"longitude\": 71.36666666666666}",
    "{\"location\": \"Hazrat-e_Turkestan\", \"latitude\": 43.301944444444445, \"longitude\": 68.26916666666666}",
    "{\"location\": \"Almaty\", \"latitude\": 43.277499999999996, \"longitude\": 76.89583333333334}",
    "{\"location\": \"Issyk_kul\", \"latitude\": 42.416666666666664, \"longitude\": 77.25}",
    "{\"location\": \"Tokmok\", \"latitude\": 42.833333333333336, \"longitude\": 75.28333333333333}",
    "{\"location\": \"Bishkek\", \"latitude\": 42.874722222222225, \"longitude\": 74.61222222222221}",
    "{\"location\": \"Osh\", \"latitude\": 40.53, \"longitude\": 72.8}",
    "{\"location\": \"Balkh\", \"latitude\": 36.75805555555556, \"longitude\": 66.89805555555556}",
    "{\"location\": \"Herat\", \"latitude\": 34.341944444444444, \"longitude\": 62.20305555555556}",
    "{\"location\": \"Alexandria_Arachosia\", \"latitude\": 31.602222222222224, \"longitude\": 65.6588888888889}",
    "{\"location\": \"Bamyan_Afghanistan\", \"latitude\": 34.825, \"longitude\": 67.83333333333333}",
    "{\"location\": \"Kabul\", \"latitude\": 34.525277777777774, \"longitude\": 69.17833333333334}",
    "{\"location\": \"Peshawar\", \"latitude\": 34.01444444444444, \"longitude\": 71.5675}",
    "{\"location\": \"Pushkalavati\", \"latitude\": 34.168055555555554, \"longitude\": 71.73611111111111}",
    "{\"location\": \"Takshashila\", \"latitude\": 33.74583333333334, \"longitude\": 72.7875}",
    "{\"location\": \"Multan\", \"latitude\": 30.197777777777777, \"longitude\": 71.46972222222223}",
    "{\"location\": \"Banbhore\", \"latitude\": 24.75138888888889, \"longitude\": 67.5213888888889}",
    "{\"location\": \"Leh\", \"latitude\": 34.16416666666667, \"longitude\": 77.58472222222221}",
    "{\"location\": \"Jaisalmer\", \"latitude\": 26.913055555555555, \"longitude\": 70.915}",
    "{\"location\": \"Mathura\", \"latitude\": 27.4925, \"longitude\": 77.67361111111111}",
    "{\"location\": \"Varanasi\", \"latitude\": 25.31888888888889, \"longitude\": 83.01277777777777}",
    "{\"location\": \"Pataliputra\", \"latitude\": 25.6125, \"longitude\": 85.12833333333333}",
    "{\"location\": \"Kathmandu\", \"latitude\": 27.71722222222222, \"longitude\": 85.32388888888889}",
    "{\"location\": \"Wari-Bateshwar\", \"latitude\": 24.093055555555555, \"longitude\": 90.82555555555555}",
    "{\"location\": \"Mahasthangarh\", \"latitude\": 24.961111111111112, \"longitude\": 89.34277777777777}",
    "{\"location\": \"Bikrampur\", \"latitude\": 23.55, \"longitude\": 90.55}",
    "{\"location\": \"Somapura_Mahavihara\", \"latitude\": 25.03111111111111, \"longitude\": 88.97722222222222}",
    "{\"location\": \"Bhitargarh\", \"latitude\": 26.45, \"longitude\": 88.61}",
    "{\"location\": \"Sonargaon\", \"latitude\": 23.6475, \"longitude\": 90.59777777777778}",
    "{\"location\": \"Chittagong\", \"latitude\": 22.334999999999997, \"longitude\": 91.8325}",
    "{\"location\": \"Comilla\", \"latitude\": 23.45, \"longitude\": 91.2}",
    "{\"location\": \"Jakar\", \"latitude\": 27.55, \"longitude\": 90.73333333333333}",
    "{\"location\": \"Paro_Bhutan\", \"latitude\": 27.433333333333334, \"longitude\": 89.41666666666667}",
    "{\"location\": \"Kashgar\", \"latitude\": 39.46805555555556, \"longitude\": 75.99388888888889}",
    "{\"location\": \"Aksu_Xinjiang\", \"latitude\": 41.184999999999995, \"longitude\": 80.29027777777777}",
    "{\"location\": \"Korla\", \"latitude\": 41.725833333333334, \"longitude\": 86.17472222222223}",
    "{\"location\": \"Loulan_(town)\", \"latitude\": 40.527633333333334, \"longitude\": 89.84064444444444}",
    "{\"location\": \"Karasahr\", \"latitude\": 42.058611111111105, \"longitude\": 86.56833333333333}",
    "{\"location\": \"Turpan\", \"latitude\": 42.95111111111111, \"longitude\": 89.18944444444445}",
    "{\"location\": \"Gaochang\", \"latitude\": 42.85277777777778, \"longitude\": 89.52916666666667}",
    "{\"location\": \"Chang%27an\", \"latitude\": 34.266666666666666, \"longitude\": 108.9}",
    "{\"location\": \"Kumul_(city)\", \"latitude\": 42.81916666666667, \"longitude\": 93.515}",
    "{\"location\": \"%C3%9Cr%C3%BCmqi\", \"latitude\": 43.822500000000005, \"longitude\": 87.6125}",
    "{\"location\": \"Yumen_Pass\", \"latitude\": 40.353500000000004, \"longitude\": 93.86402777777778}",
    "{\"location\": \"Anxi_(Arsacid_territories)\", \"latitude\": 39.833333333333336, \"longitude\": 97.56666666666666}",
    "{\"location\": \"Kashgar\", \"latitude\": 39.46805555555556, \"longitude\": 75.99388888888889}",
    "{\"location\": \"Yarkant_County\", \"latitude\": 38.39083333333333, \"longitude\": 77.22333333333333}",
    "{\"location\": \"Pishan_County\", \"latitude\": 37.61666666666667, \"longitude\": 78.28333333333333}",
    "{\"location\": \"Hotan\", \"latitude\": 37.1, \"longitude\": 80.01666666666667}",
    "{\"location\": \"Niya_(Tarim_Basin)\", \"latitude\": 38.021388888888886, \"longitude\": 82.7375}",
    "{\"location\": \"Minfeng_Town\", \"latitude\": 37.05, \"longitude\": 82.68333333333334}",
    "{\"location\": \"Endere\", \"latitude\": 37.6, \"longitude\": 83.8}",
    "{\"location\": \"Waxxari\", \"latitude\": 38.683055555555555, \"longitude\": 87.32972222222222}",
    "{\"location\": \"Ruoqiang_Town\", \"latitude\": 39.018055555555556, \"longitude\": 88.16805555555555}",
    "{\"location\": \"Miran_(China)\", \"latitude\": 39.25, \"longitude\": 88.81666666666666}",
    "{\"location\": \"Yangguan\", \"latitude\": 39.92725, \"longitude\": 94.05902777777777}",
    "{\"location\": \"Dunhuang\", \"latitude\": 40.14222222222222, \"longitude\": 94.66194444444444}",
    "{\"location\": \"Anxi_(archaeological_site)\", \"latitude\": 39.833333333333336, \"longitude\": 97.56666666666666}",
    "{\"location\": \"Dunhuang\", \"latitude\": 40.14222222222222, \"longitude\": 94.66194444444444}",
    "{\"location\": \"Jiayuguan_City\", \"latitude\": 39.77333333333333, \"longitude\": 98.28833333333333}",
    "{\"location\": \"Jiuquan\", \"latitude\": 39.733333333333334, \"longitude\": 98.49416666666667}",
    "{\"location\": \"Zhangye\", \"latitude\": 38.92472222222222, \"longitude\": 100.45}",
    "{\"location\": \"Shandan_County\", \"latitude\": 38.78638888888889, \"longitude\": 101.08888888888889}",
    "{\"location\": \"Wuwei_Gansu\", \"latitude\": 37.928888888888885, \"longitude\": 102.63805555555557}",
    "{\"location\": \"Tianzhu_County,_Guizhou\", \"latitude\": 26.90972222222222, \"longitude\": 109.20777777777778}",
    "{\"location\": \"Lanzhou\", \"latitude\": 36.06055555555555, \"longitude\": 103.82666666666667}",
    "{\"location\": \"Tianshui\", \"latitude\": 34.581388888888895, \"longitude\": 105.72472222222223}",
    "{\"location\": \"Baoji\", \"latitude\": 34.363055555555555, \"longitude\": 107.23805555555556}",
    "{\"location\": \"Chang%27an\", \"latitude\": 34.266666666666666, \"longitude\": 108.9}",
    "{\"location\": \"Pyongyang\", \"latitude\": 39.019444444444446, \"longitude\": 125.73805555555556}",
    "{\"location\": \"Gyeongju\", \"latitude\": 35.85, \"longitude\": 129.21666666666667}",
    "{\"location\": \"Busan\", \"latitude\": 35.166666666666664, \"longitude\": 129.06666666666666}",
    "{\"location\": \"Seoul\", \"latitude\": 37.559999999999995, \"longitude\": 126.99}",
    "{\"location\": \"Nara_Nara\", \"latitude\": 34.68333333333333, \"longitude\": 135.8}",
    "{\"location\": \"Fukuoka\", \"latitude\": 33.583333333333336, \"longitude\": 130.4}",
    "{\"location\": \"Nagasaki\", \"latitude\": 32.74472222222222, \"longitude\": 129.87361111111113}",
    "{\"location\": \"Osaka\", \"latitude\": 34.693888888888885, \"longitude\": 135.50222222222223}"
]
}